colorlogger/__init__.py
colorlogger-1.0.dist-info/METADATA
colorlogger-1.0.dist-info/RECORD
colorlogger-1.0.dist-info/WHEEL
colorlogger-1.0.dist-info/top_level.txt
