Metadata-Version: 2.1
Name: colorlogger
Version: 1.0
Summary: Easily log in color
Home-page: https://github.com/PokeTec/colorlogger
Author: PokestarFan
Author-email: pokestarfan@yahoo.com
Maintainer: PokestarFan
Maintainer-email: pokestarfan@yahoo.com
License: MIT License
Platform: Windows
Platform: Mac
Platform: Linux
Classifier: Development Status :: 5 - Production/Stable
Classifier: Intended Audience :: Developers
Classifier: License :: OSI Approved :: MIT License
Classifier: Natural Language :: English
Classifier: Operating System :: Microsoft :: Windows
Classifier: Operating System :: Unix
Classifier: Programming Language :: Python
Classifier: Programming Language :: Python :: 3
Classifier: Programming Language :: Python :: 3.6
Classifier: Topic :: Software Development :: Libraries :: Python Modules
Classifier: Topic :: Software Development :: Testing
Classifier: Topic :: Utilities
Requires-Dist: colorlog
